LICENSE
README.md
setup.cfg
setup.py
kooPy/KooPy.py
kooPy/__init__.py
kooPy.egg-info/PKG-INFO
kooPy.egg-info/SOURCES.txt
kooPy.egg-info/dependency_links.txt
kooPy.egg-info/top_level.txt