Metadata-Version: 2.1
Name: kooPy
Version: 0.4
Summary: KooPy: Koo for Python!
Home-page: https://github.com/nick2580/KooPy
Author: Nikhil
Author-email: nikhil.bhamere@gmail.com
License: MIT
Download-URL: https://github.com/nick2580/KooPy/archive/refs/tags/0.4.tar.gz
Keywords: kooapp,koo,koopy
Platform: UNKNOWN
Classifier: Development Status :: 3 - Alpha
Classifier: Intended Audience :: Developers
Classifier: Topic :: Software Development :: Build Tools
Classifier: License :: OSI Approved :: MIT License
Classifier: Programming Language :: Python :: 3
Classifier: Programming Language :: Python :: 3.4
Classifier: Programming Language :: Python :: 3.5
Classifier: Programming Language :: Python :: 3.6
License-File: LICENSE
